better_pynamite
