Metadata-Version: 2.1
Name: better-pynamite
Version: 0.1.4
Summary: Import and create chaos
Home-page: https://github.com/deutranium/better_pynamite
Author: Kshitijaa Jaglan
Author-email: kshitijaa.jaglan@research.iiit.ac.in
License: Apache License 2.0
Keywords: python,chaos
License-File: LICENSE
